promptbot/__init__.py
promptbot/plugin.py
promptbot/prompt.py
promptbot-0.0.2a1.dist-info/LICENSE
promptbot-0.0.2a1.dist-info/METADATA
promptbot-0.0.2a1.dist-info/WHEEL
promptbot-0.0.2a1.dist-info/top_level.txt
promptbot-0.0.2a1.dist-info/RECORD
