Metadata-Version: 2.1
Name: promptbot
Version: 0.0.2a1
Summary: A Python package for generating prompt bots on top of OpenAI GTP Apis.
Author: Clayton Bezuidenhout
Author-email: claytonbez.nl@gmail.com
Classifier: Programming Language :: Python :: 3
Classifier: License :: OSI Approved :: MIT License
Classifier: Operating System :: OS Independent
License-File: LICENSE
Requires-Dist: toml (==0.10.2)
Requires-Dist: openai (==0.27.5)
Requires-Dist: colorama (==0.4.6)
